[
    {
        "slug": "cloud-computing",
        "icon": "fa-duotone fa-cloud",
        "translations": [
            {
                "locale": "en",
                "name": "Cloud Computing"
            },
            {
                "locale": "km",
                "name": "គណនាពពក"
            }
        ]
    },
    {
        "slug": "cybersecurity",
        "icon": "fa-duotone fa-shield-halved",
        "translations": [
            {
                "locale": "en",
                "name": "Cybersecurity"
            },
            {
                "locale": "km",
                "name": "សន្តិសុខសាយបឺរ"
            }
        ]
    },
    {
        "slug": "networking",
        "icon": "fa-duotone fa-network-wired",
        "translations": [
            {
                "locale": "en",
                "name": "Networking"
            },
            {
                "locale": "km",
                "name": "បណ្តាញ"
            }
        ]
    },
    {
        "slug": "data-backup",
        "icon": "fa-duotone fa-database",
        "translations": [
            {
                "locale": "en",
                "name": "Data Backup"
            },
            {
                "locale": "km",
                "name": "ការបម្រុងទុកទិន្នន័យ"
            }
        ]
    },
    {
        "slug": "disaster-recovery",
        "icon": "fa-duotone fa-cloud-arrow-up",
        "translations": [
            {
                "locale": "en",
                "name": "Disaster Recovery"
            },
            {
                "locale": "km",
                "name": "ការស្ដារឡើងវិញក្រោយគ្រោះថ្នាក់"
            }
        ]
    },
    {
        "slug": "software-development",
        "icon": "fa-duotone fa-code",
        "translations": [
            {
                "locale": "en",
                "name": "Software Development"
            },
            {
                "locale": "km",
                "name": "ការអភិវឌ្ឍកម្មវិធី"
            }
        ]
    },
    {
        "slug": "mobile-apps",
        "icon": "fa-duotone fa-mobile-screen",
        "translations": [
            {
                "locale": "en",
                "name": "Mobile Apps"
            },
            {
                "locale": "km",
                "name": "កម្មវិធីទូរស័ព្ទ"
            }
        ]
    },
    {
        "slug": "web-development",
        "icon": "fa-duotone fa-globe",
        "translations": [
            {
                "locale": "en",
                "name": "Web Development"
            },
            {
                "locale": "km",
                "name": "ការអភិវឌ្ឍគេហទំព័រ"
            }
        ]
    },
    {
        "slug": "ui-ux-design",
        "icon": "fa-duotone fa-bezier-curve",
        "translations": [
            {
                "locale": "en",
                "name": "UI/UX Design"
            },
            {
                "locale": "km",
                "name": "ការរចនាមុខងារ និងបទពិសោធន៍អ្នកប្រើប្រាស់"
            }
        ]
    },
    {
        "slug": "it-consulting",
        "icon": "fa-duotone fa-user-tie",
        "translations": [
            {
                "locale": "en",
                "name": "IT Consulting"
            },
            {
                "locale": "km",
                "name": "ការប្រឹក្សា IT"
            }
        ]
    },
    {
        "slug": "technical-support",
        "icon": "fa-duotone fa-headset",
        "translations": [
            {
                "locale": "en",
                "name": "Technical Support"
            },
            {
                "locale": "km",
                "name": "ការគាំទ្របច្ចេកទេស"
            }
        ]
    },
    {
        "slug": "server-management",
        "icon": "fa-duotone fa-server",
        "translations": [
            {
                "locale": "en",
                "name": "Server Management"
            },
            {
                "locale": "km",
                "name": "ការគ្រប់គ្រងម៉ាស៊ីនបម្រើ"
            }
        ]
    },
    {
        "slug": "database-administration",
        "icon": "fa-duotone fa-database",
        "translations": [
            {
                "locale": "en",
                "name": "Database Administration"
            },
            {
                "locale": "km",
                "name": "ការគ្រប់គ្រងមូលដ្ឋានទិន្នន័យ"
            }
        ]
    },
    {
        "slug": "system-integration",
        "icon": "fa-duotone fa-diagram-project",
        "translations": [
            {
                "locale": "en",
                "name": "System Integration"
            },
            {
                "locale": "km",
                "name": "ការរួមបញ្ចូលប្រព័ន្ធ"
            }
        ]
    },
    {
        "slug": "digital-transformation",
        "icon": "fa-duotone fa-laptop-code",
        "translations": [
            {
                "locale": "en",
                "name": "Digital Transformation"
            },
            {
                "locale": "km",
                "name": "ការផ្លាស់ប្តូរឌីជីថល"
            }
        ]
    },
    {
        "slug": "cloud-migration",
        "icon": "fa-duotone fa-cloud-arrow-up",
        "translations": [
            {
                "locale": "en",
                "name": "Cloud Migration"
            },
            {
                "locale": "km",
                "name": "ការផ្លាស់ទីទៅពពក"
            }
        ]
    },
    {
        "slug": "ai-solutions",
        "icon": "fa-duotone fa-robot",
        "translations": [
            {
                "locale": "en",
                "name": "AI Solutions"
            },
            {
                "locale": "km",
                "name": "ដំណោះស្រាយ AI"
            }
        ]
    },
    {
        "slug": "machine-learning",
        "icon": "fa-duotone fa-brain",
        "translations": [
            {
                "locale": "en",
                "name": "Machine Learning"
            },
            {
                "locale": "km",
                "name": "ការរៀនដោយម៉ាស៊ីន"
            }
        ]
    },
    {
        "slug": "data-analytics",
        "icon": "fa-duotone fa-chart-line",
        "translations": [
            {
                "locale": "en",
                "name": "Data Analytics"
            },
            {
                "locale": "km",
                "name": "វិភាគទិន្នន័យ"
            }
        ]
    },
    {
        "slug": "business-intelligence",
        "icon": "fa-duotone fa-chart-pie",
        "translations": [
            {
                "locale": "en",
                "name": "Business Intelligence"
            },
            {
                "locale": "km",
                "name": "បញ្ញាអាជីវកម្ម"
            }
        ]
    },
    {
        "slug": "erp-solutions",
        "icon": "fa-duotone fa-cubes",
        "translations": [
            {
                "locale": "en",
                "name": "ERP Solutions"
            },
            {
                "locale": "km",
                "name": "ដំណោះស្រាយ ERP"
            }
        ]
    },
    {
        "slug": "crm-systems",
        "icon": "fa-duotone fa-handshake",
        "translations": [
            {
                "locale": "en",
                "name": "CRM Systems"
            },
            {
                "locale": "km",
                "name": "ប្រព័ន្ធ CRM"
            }
        ]
    },
    {
        "slug": "virtualization",
        "icon": "fa-duotone fa-vr-cardboard",
        "translations": [
            {
                "locale": "en",
                "name": "Virtualization"
            },
            {
                "locale": "km",
                "name": "ការធ្វើឲ្យជា​ជាក់ស្តែង​និយម"
            }
        ]
    },
    {
        "slug": "it-outsourcing",
        "icon": "fa-duotone fa-handshake-simple",
        "translations": [
            {
                "locale": "en",
                "name": "IT Outsourcing"
            },
            {
                "locale": "km",
                "name": "ការបញ្ចេញសេវា IT ខាងក្រៅ"
            }
        ]
    },
    {
        "slug": "cloud-security",
        "icon": "fa-duotone fa-lock-cloud",
        "translations": [
            {
                "locale": "en",
                "name": "Cloud Security"
            },
            {
                "locale": "km",
                "name": "សន្តិសុខពពក"
            }
        ]
    },
    {
        "slug": "firewall-protection",
        "icon": "fa-duotone fa-firewall",
        "translations": [
            {
                "locale": "en",
                "name": "Firewall Protection"
            },
            {
                "locale": "km",
                "name": "ការការពារបង្ហាប់ភ្លើង"
            }
        ]
    },
    {
        "slug": "email-security",
        "icon": "fa-duotone fa-envelope-shield",
        "translations": [
            {
                "locale": "en",
                "name": "Email Security"
            },
            {
                "locale": "km",
                "name": "សន្តិសុខអ៊ីមែល"
            }
        ]
    },
    {
        "slug": "endpoint-protection",
        "icon": "fa-duotone fa-shield-virus",
        "translations": [
            {
                "locale": "en",
                "name": "Endpoint Protection"
            },
            {
                "locale": "km",
                "name": "ការការពារទីបញ្ចប់"
            }
        ]
    },
    {
        "slug": "vpn-services",
        "icon": "fa-duotone fa-route-shield",
        "translations": [
            {
                "locale": "en",
                "name": "VPN Services"
            },
            {
                "locale": "km",
                "name": "សេវា VPN"
            }
        ]
    },
    {
        "slug": "hardware-installation",
        "icon": "fa-duotone fa-screwdriver-wrench",
        "translations": [
            {
                "locale": "en",
                "name": "Hardware Installation"
            },
            {
                "locale": "km",
                "name": "ការដំឡើងផ្នែករឹង"
            }
        ]
    },
    {
        "slug": "it-training",
        "icon": "fa-duotone fa-chalkboard-user",
        "translations": [
            {
                "locale": "en",
                "name": "IT Training"
            },
            {
                "locale": "km",
                "name": "ការបណ្តុះបណ្តាល IT"
            }
        ]
    },
    {
        "slug": "project-management",
        "icon": "fa-duotone fa-list-check",
        "translations": [
            {
                "locale": "en",
                "name": "Project Management"
            },
            {
                "locale": "km",
                "name": "ការគ្រប់គ្រងគម្រោង"
            }
        ]
    },
    {
        "slug": "cloud-hosting",
        "icon": "fa-duotone fa-server-cloud",
        "translations": [
            {
                "locale": "en",
                "name": "Cloud Hosting"
            },
            {
                "locale": "km",
                "name": "សេវាផ្តល់ទំនិញពពក"
            }
        ]
    },
    {
        "slug": "devops",
        "icon": "fa-duotone fa-infinity",
        "translations": [
            {
                "locale": "en",
                "name": "DevOps"
            },
            {
                "locale": "km",
                "name": "ការអភិវឌ្ឍន៍ និងប្រតិបត្តិការ"
            }
        ]
    },
    {
        "slug": "containerization",
        "icon": "fa-duotone fa-box-open-full",
        "translations": [
            {
                "locale": "en",
                "name": "Containerization"
            },
            {
                "locale": "km",
                "name": "ការប្រើបច្ចេកវិទ្យា Container"
            }
        ]
    },
    {
        "slug": "blockchain-technology",
        "icon": "fa-duotone fa-cubes-stacked",
        "translations": [
            {
                "locale": "en",
                "name": "Blockchain Technology"
            },
            {
                "locale": "km",
                "name": "បច្ចេកវិទ្យា Blockchain"
            }
        ]
    },
    {
        "slug": "iot-solutions",
        "icon": "fa-duotone fa-tower-cell",
        "translations": [
            {
                "locale": "en",
                "name": "IoT Solutions"
            },
            {
                "locale": "km",
                "name": "ដំណោះស្រាយ IoT"
            }
        ]
    },
    {
        "slug": "network-security",
        "icon": "fa-duotone fa-lock-network",
        "translations": [
            {
                "locale": "en",
                "name": "Network Security"
            },
            {
                "locale": "km",
                "name": "សន្តិសុខបណ្តាញ"
            }
        ]
    },
    {
        "slug": "digital-marketing",
        "icon": "fa-duotone fa-bullhorn",
        "translations": [
            {
                "locale": "en",
                "name": "Digital Marketing"
            },
            {
                "locale": "km",
                "name": "ទីផ្សារឌីជីថល"
            }
        ]
    },
    {
        "slug": "seo-services",
        "icon": "fa-duotone fa-magnifying-glass-chart",
        "translations": [
            {
                "locale": "en",
                "name": "SEO Services"
            },
            {
                "locale": "km",
                "name": "សេវា SEO"
            }
        ]
    },
    {
        "slug": "social-media-management",
        "icon": "fa-duotone fa-share-nodes",
        "translations": [
            {
                "locale": "en",
                "name": "Social Media Management"
            },
            {
                "locale": "km",
                "name": "ការគ្រប់គ្រងបណ្តាញសង្គម"
            }
        ]
    },
    {
        "slug": "branding-and-design",
        "icon": "fa-duotone fa-palette",
        "translations": [
            {
                "locale": "en",
                "name": "Branding & Design"
            },
            {
                "locale": "km",
                "name": "ម៉ាក និងការរចនា"
            }
        ]
    },
    {
        "slug": "ecommerce-solutions",
        "icon": "fa-duotone fa-cart-shopping",
        "translations": [
            {
                "locale": "en",
                "name": "E-Commerce Solutions"
            },
            {
                "locale": "km",
                "name": "ដំណោះស្រាយពាណិជ្ជកម្មអេឡិចត្រូនិក"
            }
        ]
    },
    {
        "slug": "cloud-storage",
        "icon": "fa-duotone fa-cloud-arrow-down",
        "translations": [
            {
                "locale": "en",
                "name": "Cloud Storage"
            },
            {
                "locale": "km",
                "name": "ការផ្ទុកទិន្នន័យលើពពក"
            }
        ]
    },
    {
        "slug": "password-management",
        "icon": "fa-duotone fa-key",
        "translations": [
            {
                "locale": "en",
                "name": "Password Management"
            },
            {
                "locale": "km",
                "name": "ការគ្រប់គ្រងពាក្យសម្ងាត់"
            }
        ]
    },
    {
        "slug": "rpa-automation",
        "icon": "fa-duotone fa-gears",
        "translations": [
            {
                "locale": "en",
                "name": "RPA Automation"
            },
            {
                "locale": "km",
                "name": "ការបំលែងការងារជាអូតូ"
            }
        ]
    },
    {
        "slug": "helpdesk-services",
        "icon": "fa-duotone fa-life-ring",
        "translations": [
            {
                "locale": "en",
                "name": "Helpdesk Services"
            },
            {
                "locale": "km",
                "name": "សេវាជំនួយអ្នកប្រើប្រាស់"
            }
        ]
    }
]